gktools/__init__.py
gktools/calculator.py
gktools-0.0.3.dist-info/LICENSE
gktools-0.0.3.dist-info/METADATA
gktools-0.0.3.dist-info/WHEEL
gktools-0.0.3.dist-info/top_level.txt
gktools-0.0.3.dist-info/RECORD
